lactate_thresholds/__init__.py
lactate_thresholds/app.py
lactate_thresholds/data.py
lactate_thresholds/methods.py
lactate_thresholds/plot.py
lactate_thresholds/process.py
lactate_thresholds/types.py
lactate_thresholds/utils.py
lactate_thresholds/zones.py
lactate_thresholds-0.3.8.dist-info/METADATA
lactate_thresholds-0.3.8.dist-info/WHEEL
lactate_thresholds-0.3.8.dist-info/entry_points.txt
lactate_thresholds-0.3.8.dist-info/licenses/LICENSE
lactate_thresholds-0.3.8.dist-info/RECORD
