Metadata-Version: 2.4
Name: lactate-thresholds
Version: 0.3.8
Summary: Convenience functions for analysis of lactate-intensity curves.
Author-email: bart6114 <bartsmeets86@gmail.com>, tverum <vanerum.tim@gmail.com>
License-File: LICENSE
Requires-Python: >=3.12.3
Requires-Dist: altair>=5.5.0
Requires-Dist: numpy>=2.1.3
Requires-Dist: pandas>=2.2.3
Requires-Dist: pwlf>=2.3.0
Requires-Dist: pydantic>=2.10.3
Requires-Dist: scikit-learn>=1.5.2
Requires-Dist: statsmodels>=0.14.4
Requires-Dist: streamlit>=1.40.2
